{
  "hash": "9543a81f",
  "configHash": "55f28645",
  "lockfileHash": "cefec54e",
  "browserHash": "f62494af",
  "optimized": {
    "react/jsx-dev-runtime": {
      "src": "../../node_modules/react/jsx-dev-runtime.js",
      "file": "react_jsx-dev-runtime.js",
      "fileHash": "49612de2",
      "needsInterop": true
    },
    "react": {
      "src": "../../node_modules/react/index.js",
      "file": "react.js",
      "fileHash": "d97b1505",
      "needsInterop": true
    },
    "react-dom/client": {
      "src": "../../node_modules/react-dom/client.js",
      "file": "react-dom_client.js",
      "fileHash": "a79df714",
      "needsInterop": true
    },
    "react-hot-toast": {
      "src": "../../node_modules/react-hot-toast/dist/index.mjs",
      "file": "react-hot-toast.js",
      "fileHash": "f525e2b1",
      "needsInterop": false
    },
    "react-router-dom": {
      "src": "../../node_modules/react-router-dom/dist/index.mjs",
      "file": "react-router-dom.js",
      "fileHash": "35c831de",
      "needsInterop": false
    },
    "react-redux": {
      "src": "../../node_modules/react-redux/dist/react-redux.mjs",
      "file": "react-redux.js",
      "fileHash": "d5cb2adc",
      "needsInterop": false
    },
    "framer-motion": {
      "src": "../../node_modules/framer-motion/dist/es/index.mjs",
      "file": "framer-motion.js",
      "fileHash": "0348677d",
      "needsInterop": false
    },
    "@mui/material": {
      "src": "../../node_modules/@mui/material/esm/index.js",
      "file": "@mui_material.js",
      "fileHash": "525530a8",
      "needsInterop": false
    },
    "@mui/icons-material/Add": {
      "src": "../../node_modules/@mui/icons-material/esm/Add.js",
      "file": "@mui_icons-material_Add.js",
      "fileHash": "8eec3210",
      "needsInterop": false
    },
    "@mui/icons-material/Edit": {
      "src": "../../node_modules/@mui/icons-material/esm/Edit.js",
      "file": "@mui_icons-material_Edit.js",
      "fileHash": "0a6932e5",
      "needsInterop": false
    },
    "@mui/icons-material/Visibility": {
      "src": "../../node_modules/@mui/icons-material/esm/Visibility.js",
      "file": "@mui_icons-material_Visibility.js",
      "fileHash": "769861e1",
      "needsInterop": false
    },
    "@mui/icons-material/VisibilityOff": {
      "src": "../../node_modules/@mui/icons-material/esm/VisibilityOff.js",
      "file": "@mui_icons-material_VisibilityOff.js",
      "fileHash": "72913297",
      "needsInterop": false
    },
    "@mui/icons-material/ArrowBack": {
      "src": "../../node_modules/@mui/icons-material/esm/ArrowBack.js",
      "file": "@mui_icons-material_ArrowBack.js",
      "fileHash": "6d56ae60",
      "needsInterop": false
    },
    "@mui/icons-material/Delete": {
      "src": "../../node_modules/@mui/icons-material/esm/Delete.js",
      "file": "@mui_icons-material_Delete.js",
      "fileHash": "7a0c0621",
      "needsInterop": false
    },
    "@mui/icons-material/Search": {
      "src": "../../node_modules/@mui/icons-material/esm/Search.js",
      "file": "@mui_icons-material_Search.js",
      "fileHash": "090e9795",
      "needsInterop": false
    },
    "@reduxjs/toolkit": {
      "src": "../../node_modules/@reduxjs/toolkit/dist/redux-toolkit.modern.mjs",
      "file": "@reduxjs_toolkit.js",
      "fileHash": "c2759934",
      "needsInterop": false
    },
    "axios": {
      "src": "../../node_modules/axios/index.js",
      "file": "axios.js",
      "fileHash": "03e00d66",
      "needsInterop": false
    }
  },
  "chunks": {
    "chunk-C6WWHQR7": {
      "file": "chunk-C6WWHQR7.js"
    },
    "chunk-X6EN5AMJ": {
      "file": "chunk-X6EN5AMJ.js"
    },
    "chunk-5NY4A3DM": {
      "file": "chunk-5NY4A3DM.js"
    },
    "chunk-MDEKZDDQ": {
      "file": "chunk-MDEKZDDQ.js"
    },
    "chunk-AM4NN4A5": {
      "file": "chunk-AM4NN4A5.js"
    },
    "chunk-V4OQ3NZ2": {
      "file": "chunk-V4OQ3NZ2.js"
    }
  }
}